emojihunt/__init__.py
emojihunt/emojihunt.py
emojihunt-1.1.1.dist-info/METADATA
emojihunt-1.1.1.dist-info/WHEEL
emojihunt-1.1.1.dist-info/top_level.txt
emojihunt-1.1.1.dist-info/RECORD
