Metadata-Version: 2.1
Name: emojihunt
Version: 1.1.1
Summary: UVIC ECE471 Project Code for 2023
Author: Declan McIntosh
Classifier: Programming Language :: Python :: 3
Classifier: License :: OSI Approved :: MIT License
Classifier: Operating System :: OS Independent
Requires-Python: >=3.8
Requires-Dist: keras (>=2.8.0)
Requires-Dist: imgaug (==0.4.0)
Requires-Dist: opencv-python (>=4.1.2.30)
Requires-Dist: Pillow
